trece/__init__.py
trece/__main__.py
trece/cli.py
trece/download.py
trece-0.0.0a1.dist-info/licenses/LICENSE
trece-0.0.0a1.dist-info/METADATA
trece-0.0.0a1.dist-info/WHEEL
trece-0.0.0a1.dist-info/entry_points.txt
trece-0.0.0a1.dist-info/top_level.txt
trece-0.0.0a1.dist-info/RECORD
