Metadata-Version: 2.4
Name: trece
Version: 0.0.0a1
Summary: A CLI tool for downloading authoritative Spanish geospatial and address data.
Home-page: https://github.com/ernestofgonzalez/trece
Author: Ernesto González
License: Apache License, Version 2.0
Project-URL: Source code, https://github.com/ernestofgonzalez/trece
Project-URL: Issues, https://github.com/ernestofgonzalez/trece/issues
Project-URL: CI, https://github.com/ernestofgonzalez/trece/actions
Project-URL: Changelog, https://github.com/ernestofgonzalez/trece/releases
Classifier: Intended Audience :: Developers
Classifier: Topic :: Software Development :: Libraries
Classifier: Topic :: Utilities
Classifier: Programming Language :: Python :: 3.10
Classifier: Programming Language :: Python :: 3.11
Classifier: Programming Language :: Python :: 3.12
Classifier: Programming Language :: Python :: 3.13
Classifier: Operating System :: Microsoft :: Windows
Classifier: Operating System :: POSIX
Classifier: Operating System :: Unix
Classifier: Operating System :: MacOS
Requires-Python: >=3.10
License-File: LICENSE
Requires-Dist: click
Requires-Dist: geopandas>=0.12.0
Requires-Dist: pandas>=1.5.0
Requires-Dist: playwright
Provides-Extra: test
Requires-Dist: pytest; extra == "test"
Dynamic: author
Dynamic: classifier
Dynamic: description
Dynamic: description-content-type
Dynamic: home-page
Dynamic: license
Dynamic: license-file
Dynamic: project-url
Dynamic: provides-extra
Dynamic: requires-dist
Dynamic: requires-python
Dynamic: summary
